odoo/addons/base_tier_validation_correction/README.rst
odoo/addons/base_tier_validation_correction/__init__.py
odoo/addons/base_tier_validation_correction/__manifest__.py
odoo/addons/base_tier_validation_correction/data/cron_data.xml
odoo/addons/base_tier_validation_correction/data/mail_data.xml
odoo/addons/base_tier_validation_correction/i18n/base_tier_validation_correction.pot
odoo/addons/base_tier_validation_correction/models/__init__.py
odoo/addons/base_tier_validation_correction/models/tier_correction.py
odoo/addons/base_tier_validation_correction/models/tier_validation.py
odoo/addons/base_tier_validation_correction/readme/CONFIGURE.rst
odoo/addons/base_tier_validation_correction/readme/CONTRIBUTORS.rst
odoo/addons/base_tier_validation_correction/readme/DESCRIPTION.rst
odoo/addons/base_tier_validation_correction/readme/USAGE.rst
odoo/addons/base_tier_validation_correction/security/correction_groups.xml
odoo/addons/base_tier_validation_correction/security/ir.model.access.csv
odoo/addons/base_tier_validation_correction/static/description/icon.png
odoo/addons/base_tier_validation_correction/static/description/index.html
odoo/addons/base_tier_validation_correction/templates/tier_validation_templates.xml
odoo/addons/base_tier_validation_correction/tests/__init__.py
odoo/addons/base_tier_validation_correction/tests/test_tier_validation.py
odoo/addons/base_tier_validation_correction/views/tier_correction_view.xml
odoo/addons/base_tier_validation_correction/wizards/__init__.py
odoo/addons/base_tier_validation_correction/wizards/affected_tier_reviews.py
odoo/addons/base_tier_validation_correction/wizards/affected_tier_reviews.xml
odoo14_addon_base_tier_validation_correction-14.0.1.0.2.dist-info/METADATA
odoo14_addon_base_tier_validation_correction-14.0.1.0.2.dist-info/WHEEL
odoo14_addon_base_tier_validation_correction-14.0.1.0.2.dist-info/top_level.txt
odoo14_addon_base_tier_validation_correction-14.0.1.0.2.dist-info/RECORD
